{"optimus": [1, "/categories/optimus.html", {"posts": [{"date": "12/19/2014", "url": "/posts/3_IandLinuxandNvidia.html", "isodate": "2014-12-19T22:10:48+03:30", "title": "I , Linux and NVIDIA"}]}], "google": [1, "/categories/google.html", {"posts": [{"date": "12/19/2014", "url": "/posts/2_nikola_blogging.html", "isodate": "2014-12-19T11:59:39+03:30", "title": "\u0627\u06cc\u0646 \u0628\u0644\u0627\u06af \u0686\u06af\u0648\u0646\u0647 \u0633\u0627\u062e\u062a\u0647 \u0634\u062f\u0647\u061f"}]}], "rtl": [1, "/categories/rtl.html", {"posts": [{"date": "12/26/2014", "url": "/posts/5_counting_words_graph.html", "isodate": "2014-12-26T12:37:36+03:30", "title": "\u0634\u0645\u0627\u0631\u0634 \u062f\u0641\u0639\u0627\u062a \u062a\u06a9\u0631\u0627\u0631 \u06a9\u0644\u0645\u0627\u062a \u062f\u0631 \u06cc\u06a9 \u0645\u062a\u0646 + \u0646\u0645\u0648\u062f\u0627\u0631"}]}], "hebrew": [1, "/categories/hebrew.html", {"posts": [{"date": "12/26/2014", "url": "/posts/5_counting_words_graph.html", "isodate": "2014-12-26T12:37:36+03:30", "title": "\u0634\u0645\u0627\u0631\u0634 \u062f\u0641\u0639\u0627\u062a \u062a\u06a9\u0631\u0627\u0631 \u06a9\u0644\u0645\u0627\u062a \u062f\u0631 \u06cc\u06a9 \u0645\u062a\u0646 + \u0646\u0645\u0648\u062f\u0627\u0631"}]}], "Interference": [1, "/categories/interference.html", {"posts": [{"date": "12/19/2014", "url": "/posts/3_IandLinuxandNvidia.html", "isodate": "2014-12-19T22:10:48+03:30", "title": "I , Linux and NVIDIA"}]}], "analytics": [1, "/categories/analytics.html", {"posts": [{"date": "12/19/2014", "url": "/posts/2_nikola_blogging.html", "isodate": "2014-12-19T11:59:39+03:30", "title": "\u0627\u06cc\u0646 \u0628\u0644\u0627\u06af \u0686\u06af\u0648\u0646\u0647 \u0633\u0627\u062e\u062a\u0647 \u0634\u062f\u0647\u061f"}]}], "z510": [1, "/categories/z510.html", {"posts": [{"date": "12/19/2014", "url": "/posts/3_IandLinuxandNvidia.html", "isodate": "2014-12-19T22:10:48+03:30", "title": "I , Linux and NVIDIA"}]}], "linux": [1, "/categories/linux.html", {"posts": [{"date": "12/19/2014", "url": "/posts/3_IandLinuxandNvidia.html", "isodate": "2014-12-19T22:10:48+03:30", "title": "I , Linux and NVIDIA"}]}], "arabic": [1, "/categories/arabic.html", {"posts": [{"date": "12/26/2014", "url": "/posts/5_counting_words_graph.html", "isodate": "2014-12-26T12:37:36+03:30", "title": "\u0634\u0645\u0627\u0631\u0634 \u062f\u0641\u0639\u0627\u062a \u062a\u06a9\u0631\u0627\u0631 \u06a9\u0644\u0645\u0627\u062a \u062f\u0631 \u06cc\u06a9 \u0645\u062a\u0646 + \u0646\u0645\u0648\u062f\u0627\u0631"}]}], "CMS": [1, "/categories/cms.html", {"posts": [{"date": "12/19/2014", "url": "/posts/2_nikola_blogging.html", "isodate": "2014-12-19T11:59:39+03:30", "title": "\u0627\u06cc\u0646 \u0628\u0644\u0627\u06af \u0686\u06af\u0648\u0646\u0647 \u0633\u0627\u062e\u062a\u0647 \u0634\u062f\u0647\u061f"}]}], "CPU": [2, "/categories/cpu.html", {"posts": [{"date": "12/21/2014", "url": "/posts/4_what_is_thread.html", "isodate": "2014-12-21T17:06:27+03:30", "title": "Thread \u0686\u06cc\u0633\u062a\u061f"}, {"date": "12/19/2014", "url": "/posts/3_IandLinuxandNvidia.html", "isodate": "2014-12-19T22:10:48+03:30", "title": "I , Linux and NVIDIA"}]}], "regex": [1, "/categories/regex.html", {"posts": [{"date": "12/26/2014", "url": "/posts/5_counting_words_graph.html", "isodate": "2014-12-26T12:37:36+03:30", "title": "\u0634\u0645\u0627\u0631\u0634 \u062f\u0641\u0639\u0627\u062a \u062a\u06a9\u0631\u0627\u0631 \u06a9\u0644\u0645\u0627\u062a \u062f\u0631 \u06cc\u06a9 \u0645\u062a\u0646 + \u0646\u0645\u0648\u062f\u0627\u0631"}]}], "nikola": [1, "/categories/nikola.html", {"posts": [{"date": "12/19/2014", "url": "/posts/2_nikola_blogging.html", "isodate": "2014-12-19T11:59:39+03:30", "title": "\u0627\u06cc\u0646 \u0628\u0644\u0627\u06af \u0686\u06af\u0648\u0646\u0647 \u0633\u0627\u062e\u062a\u0647 \u0634\u062f\u0647\u061f"}]}], "haswell": [1, "/categories/haswell.html", {"posts": [{"date": "12/19/2014", "url": "/posts/3_IandLinuxandNvidia.html", "isodate": "2014-12-19T22:10:48+03:30", "title": "I , Linux and NVIDIA"}]}], "bumblebee": [1, "/categories/bumblebee.html", {"posts": [{"date": "12/19/2014", "url": "/posts/3_IandLinuxandNvidia.html", "isodate": "2014-12-19T22:10:48+03:30", "title": "I , Linux and NVIDIA"}]}], "\u062f\u0631\u0627\u06cc\u0648\u0631": [1, "/categories/drywr.html", {"posts": [{"date": "12/19/2014", "url": "/posts/3_IandLinuxandNvidia.html", "isodate": "2014-12-19T22:10:48+03:30", "title": "I , Linux and NVIDIA"}]}], "libgl": [1, "/categories/libgl.html", {"posts": [{"date": "12/19/2014", "url": "/posts/3_IandLinuxandNvidia.html", "isodate": "2014-12-19T22:10:48+03:30", "title": "I , Linux and NVIDIA"}]}], "Freq": [1, "/categories/freq.html", {"posts": [{"date": "12/19/2014", "url": "/posts/3_IandLinuxandNvidia.html", "isodate": "2014-12-19T22:10:48+03:30", "title": "I , Linux and NVIDIA"}]}], "Github": [1, "/categories/github.html", {"posts": [{"date": "12/19/2014", "url": "/posts/2_nikola_blogging.html", "isodate": "2014-12-19T11:59:39+03:30", "title": "\u0627\u06cc\u0646 \u0628\u0644\u0627\u06af \u0686\u06af\u0648\u0646\u0647 \u0633\u0627\u062e\u062a\u0647 \u0634\u062f\u0647\u061f"}]}], "python": [1, "/categories/python.html", {"posts": [{"date": "12/26/2014", "url": "/posts/5_counting_words_graph.html", "isodate": "2014-12-26T12:37:36+03:30", "title": "\u0634\u0645\u0627\u0631\u0634 \u062f\u0641\u0639\u0627\u062a \u062a\u06a9\u0631\u0627\u0631 \u06a9\u0644\u0645\u0627\u062a \u062f\u0631 \u06cc\u06a9 \u0645\u062a\u0646 + \u0646\u0645\u0648\u062f\u0627\u0631"}]}], "nvidia": [1, "/categories/nvidia.html", {"posts": [{"date": "12/19/2014", "url": "/posts/3_IandLinuxandNvidia.html", "isodate": "2014-12-19T22:10:48+03:30", "title": "I , Linux and NVIDIA"}]}], "driver": [1, "/categories/driver.html", {"posts": [{"date": "12/19/2014", "url": "/posts/3_IandLinuxandNvidia.html", "isodate": "2014-12-19T22:10:48+03:30", "title": "I , Linux and NVIDIA"}]}], "chart": [1, "/categories/chart.html", {"posts": [{"date": "12/26/2014", "url": "/posts/5_counting_words_graph.html", "isodate": "2014-12-26T12:37:36+03:30", "title": "\u0634\u0645\u0627\u0631\u0634 \u062f\u0641\u0639\u0627\u062a \u062a\u06a9\u0631\u0627\u0631 \u06a9\u0644\u0645\u0627\u062a \u062f\u0631 \u06cc\u06a9 \u0645\u062a\u0646 + \u0646\u0645\u0648\u062f\u0627\u0631"}]}], "matplotlib": [1, "/categories/matplotlib.html", {"posts": [{"date": "12/26/2014", "url": "/posts/5_counting_words_graph.html", "isodate": "2014-12-26T12:37:36+03:30", "title": "\u0634\u0645\u0627\u0631\u0634 \u062f\u0641\u0639\u0627\u062a \u062a\u06a9\u0631\u0627\u0631 \u06a9\u0644\u0645\u0627\u062a \u062f\u0631 \u06cc\u06a9 \u0645\u062a\u0646 + \u0646\u0645\u0648\u062f\u0627\u0631"}]}], "\u06a9\u062a\u0627\u0628": [1, "/categories/khtb.html", {"posts": [{"date": "12/28/2014", "url": "/posts/6_yar_e_mehraban.html", "isodate": "2014-12-28T21:50:52+03:30", "title": "\u06cc\u0627\u0631 \u0645\u0647\u0631\u0628\u0627\u0646"}]}], "Joomla": [1, "/categories/joomla.html", {"posts": [{"date": "12/19/2014", "url": "/posts/2_nikola_blogging.html", "isodate": "2014-12-19T11:59:39+03:30", "title": "\u0627\u06cc\u0646 \u0628\u0644\u0627\u06af \u0686\u06af\u0648\u0646\u0647 \u0633\u0627\u062e\u062a\u0647 \u0634\u062f\u0647\u061f"}]}], "graphic": [1, "/categories/graphic.html", {"posts": [{"date": "12/19/2014", "url": "/posts/3_IandLinuxandNvidia.html", "isodate": "2014-12-19T22:10:48+03:30", "title": "I , Linux and NVIDIA"}]}], "ubuntu": [1, "/categories/ubuntu.html", {"posts": [{"date": "12/19/2014", "url": "/posts/3_IandLinuxandNvidia.html", "isodate": "2014-12-19T22:10:48+03:30", "title": "I , Linux and NVIDIA"}]}], "disqus": [1, "/categories/disqus.html", {"posts": [{"date": "12/19/2014", "url": "/posts/2_nikola_blogging.html", "isodate": "2014-12-19T11:59:39+03:30", "title": "\u0627\u06cc\u0646 \u0628\u0644\u0627\u06af \u0686\u06af\u0648\u0646\u0647 \u0633\u0627\u062e\u062a\u0647 \u0634\u062f\u0647\u061f"}]}], "Injection": [1, "/categories/injection.html", {"posts": [{"date": "12/19/2014", "url": "/posts/2_nikola_blogging.html", "isodate": "2014-12-19T11:59:39+03:30", "title": "\u0627\u06cc\u0646 \u0628\u0644\u0627\u06af \u0686\u06af\u0648\u0646\u0647 \u0633\u0627\u062e\u062a\u0647 \u0634\u062f\u0647\u061f"}]}], "nouveau": [1, "/categories/nouveau.html", {"posts": [{"date": "12/19/2014", "url": "/posts/3_IandLinuxandNvidia.html", "isodate": "2014-12-19T22:10:48+03:30", "title": "I , Linux and NVIDIA"}]}], "laptops": [1, "/categories/laptops.html", {"posts": [{"date": "12/19/2014", "url": "/posts/3_IandLinuxandNvidia.html", "isodate": "2014-12-19T22:10:48+03:30", "title": "I , Linux and NVIDIA"}]}], "lenovo": [1, "/categories/lenovo.html", {"posts": [{"date": "12/19/2014", "url": "/posts/3_IandLinuxandNvidia.html", "isodate": "2014-12-19T22:10:48+03:30", "title": "I , Linux and NVIDIA"}]}], "intel": [1, "/categories/intel.html", {"posts": [{"date": "12/19/2014", "url": "/posts/3_IandLinuxandNvidia.html", "isodate": "2014-12-19T22:10:48+03:30", "title": "I , Linux and NVIDIA"}]}], "thread": [1, "/categories/thread.html", {"posts": [{"date": "12/21/2014", "url": "/posts/4_what_is_thread.html", "isodate": "2014-12-21T17:06:27+03:30", "title": "Thread \u0686\u06cc\u0633\u062a\u061f"}]}], "contex": [1, "/categories/contex.html", {"posts": [{"date": "12/21/2014", "url": "/posts/4_what_is_thread.html", "isodate": "2014-12-21T17:06:27+03:30", "title": "Thread \u0686\u06cc\u0633\u062a\u061f"}]}], "switch": [1, "/categories/switch.html", {"posts": [{"date": "12/21/2014", "url": "/posts/4_what_is_thread.html", "isodate": "2014-12-21T17:06:27+03:30", "title": "Thread \u0686\u06cc\u0633\u062a\u061f"}]}], "cuda": [2, "/categories/cuda.html", {"posts": [{"date": "12/21/2014", "url": "/posts/4_what_is_thread.html", "isodate": "2014-12-21T17:06:27+03:30", "title": "Thread \u0686\u06cc\u0633\u062a\u061f"}, {"date": "12/19/2014", "url": "/posts/3_IandLinuxandNvidia.html", "isodate": "2014-12-19T22:10:48+03:30", "title": "I , Linux and NVIDIA"}]}], "SQL": [1, "/categories/sql.html", {"posts": [{"date": "12/19/2014", "url": "/posts/2_nikola_blogging.html", "isodate": "2014-12-19T11:59:39+03:30", "title": "\u0627\u06cc\u0646 \u0628\u0644\u0627\u06af \u0686\u06af\u0648\u0646\u0647 \u0633\u0627\u062e\u062a\u0647 \u0634\u062f\u0647\u061f"}]}], "Wordpress": [1, "/categories/wordpress.html", {"posts": [{"date": "12/19/2014", "url": "/posts/2_nikola_blogging.html", "isodate": "2014-12-19T11:59:39+03:30", "title": "\u0627\u06cc\u0646 \u0628\u0644\u0627\u06af \u0686\u06af\u0648\u0646\u0647 \u0633\u0627\u062e\u062a\u0647 \u0634\u062f\u0647\u061f"}]}]}